pymonctl/__init__.py
pymonctl/_main.py
pymonctl/_pymonctl_linux.py
pymonctl/_pymonctl_macos.py
pymonctl/_pymonctl_win.py
pymonctl/_structs.py
pymonctl/py.typed
PyMonCtl-0.91.dist-info/AUTHORS.txt
PyMonCtl-0.91.dist-info/LICENSE.txt
PyMonCtl-0.91.dist-info/METADATA
PyMonCtl-0.91.dist-info/WHEEL
PyMonCtl-0.91.dist-info/top_level.txt
PyMonCtl-0.91.dist-info/RECORD
