Metadata-Version: 2.1
Name: PyMonCtl
Version: 0.91
Summary: Cross-Platform toolkit to get info on and control monitors connected
Home-page: https://github.com/Kalmat/PyMonCtl
Author: Kalmat
Author-email: palookjones@gmail.com
License: BSD 3
Keywords: screen display monitor control geometry size position frequency scale orientation screen-size mouse-position
Classifier: Development Status :: 4 - Beta
Classifier: Environment :: Win32 (MS Windows)
Classifier: Environment :: X11 Applications
Classifier: Environment :: MacOS X
Classifier: Intended Audience :: Developers
Classifier: License :: OSI Approved :: BSD License
Classifier: Operating System :: OS Independent
Classifier: Programming Language :: Python
Classifier: Programming Language :: Python :: 3
Classifier: Programming Language :: Python :: 3 :: Only
Classifier: Programming Language :: Python :: 3.9
Classifier: Programming Language :: Python :: 3.10
Classifier: Programming Language :: Python :: 3.11
License-File: LICENSE.txt
License-File: AUTHORS.txt
Requires-Dist: typing-extensions >=4.4.0
Requires-Dist: pyobjc >=8.1 ; sys_platform == "darwin"
Requires-Dist: python-xlib >=0.21 ; sys_platform == "linux"
Requires-Dist: ewmhlib >=0.1 ; sys_platform == "linux"
Requires-Dist: pywin32 >=302 ; sys_platform == "win32"
Provides-Extra: dev
Requires-Dist: types-setuptools >=65.5 ; extra == 'dev'
Requires-Dist: mypy >=0.990 ; extra == 'dev'
Requires-Dist: types-pywin32 >=305.0.0.3 ; extra == 'dev'
Requires-Dist: types-python-xlib >=0.32 ; extra == 'dev'
Requires-Dist: pywinctl >=0.3 ; extra == 'dev'
